__init__.py
o2a_lib/__init__.py
o2a_lib/el_fs_functions.py
o2a_lib/el_parser.py
o2a_lib/el_wf_functions.py
o2a_lib/functions.py
o2a_lib/property_utils.py
o2a_lib_acceldata-2.0.1.dist-info/licenses/LICENSE
o2a_lib_acceldata-2.0.1.dist-info/METADATA
o2a_lib_acceldata-2.0.1.dist-info/WHEEL
o2a_lib_acceldata-2.0.1.dist-info/top_level.txt
o2a_lib_acceldata-2.0.1.dist-info/RECORD
