Metadata-Version: 2.4
Name: o2a_lib-acceldata
Version: 2.0.1
Summary: Additional library for Oozie To Airflow migration tool
Author-email: Jarek Potiuk <jarek.potiuk@polidea.com>, Szymon Przedwojski <szymon.przedwojski@polidea.com>, Kamil Breguła <kamil.bregula@polidea.com>, Feng Lu <fenglu@google.com>, Cameron Moberg <cjmoberg@google.com>, Sehaj <sehaj@acceldata.io>
Project-URL: Homepage, https://github.com/acceldata-io/o2a
Project-URL: Bug Tracker, https://github.com/acceldata-io/o2a/issues
Classifier: Programming Language :: Python :: 3.8
Classifier: Programming Language :: Python :: 3.9
Classifier: Programming Language :: Python :: 3.10
Classifier: Programming Language :: Python :: 3.11
Classifier: License :: OSI Approved :: Apache Software License
Classifier: Operating System :: OS Independent
Requires-Python: >=3.8
License-File: LICENSE
Dynamic: license-file
